{
  "catalog_id": "payroll-parameters-synthetic-v1",
  "version": "1.1.0",
  "scope": "Fixtures synthetiques LOT 4D pour modeliser des parametres de paie sans valeur INEOS applicable",
  "fixture_type": "synthetic_example",
  "security_notice": "Exemple synthetique uniquement. Les valeurs ne doivent pas etre appliquees a un salarie ni reutilisees comme droits INEOS.",
  "parameters": [
    {
      "parameter_id": "PARAM_DUREE_MENSUELLE_REF_SYN",
      "parameter_code": "DUREE_MENS_REF_SYN",
      "label": "Duree mensuelle de reference synthetique",
      "business_description": "Parametre fictif permettant d'identifier la duree mensuelle necessaire a certains controles de paie.",
      "data_role": "source_data",
      "parameter_type": "duration",
      "value_state": "synthetic_test_value",
      "value_kind": "entered_data",
      "value": { "raw": "123,45 heures - valeur fictive non applicable", "numeric_value": 123.45, "unit": "hours", "currency": null, "percentage": null, "is_fallback_value": false },
      "employee_population": ["tous"],
      "work_schedule": ["tous_regimes"],
      "application_period": { "label": "periode fictive ouverte", "start_date": "2026-01-01", "end_date": null, "notes": ["Periode synthetique pour tests uniquement."] },
      "source_layer": "synthetic_fixture",
      "source_document": "Fixture synthetique LOT 4D - duree mensuelle",
      "source_reference": "fixture:param:duree-mensuelle",
      "effective_date": "2026-01-01",
      "end_date": null,
      "linked_rule_ids": ["PAY_HSUP_TRANCHES_001"],
      "linked_variables": ["base_horaire", "periode"],
      "linked_nibelis_rubric_ids": ["NIB_RUB_SALAIRE_BASE", "NIB_RUB_HSUP_BASE"],
      "linked_kelio_counter_ids": ["KELIO_HS_SYN"],
      "calculation_allowed": false,
      "legal_priority": "to_verify",
      "validation_status": "synthetic_example",
      "human_validation": { "status": "pending", "validator": "expert_paie_humain", "validated_at": null, "notes": ["Valeur fictive non validee."] },
      "confidence": "low",
      "confidentiality": "internal",
      "verified_by": "expert_paie_humain",
      "last_checked_at": null,
      "validation_documents": ["accord temps de travail a verifier", "bulletin anonymise futur"],
      "misuse_risks": ["Transformer une duree fictive en base de calcul reelle."],
      "mutually_exclusive_group": null,
      "synthetic_only": true,
      "notes": ["Valeur pedagogique volontairement non applicable."]
    },
    {
      "parameter_id": "PARAM_DUREE_HEBDO_REF_SYN",
      "parameter_code": "DUREE_HEBDO_REF_SYN",
      "label": "Duree hebdomadaire de reference synthetique",
      "business_description": "Parametre fictif representant une duree hebdomadaire utile au controle du declenchement d'heures.",
      "data_role": "source_data",
      "parameter_type": "duration",
      "value_state": "synthetic_test_value",
      "value_kind": "entered_data",
      "value": { "raw": "12,34 heures - valeur fictive non applicable", "numeric_value": 12.34, "unit": "hours", "currency": null, "percentage": null, "is_fallback_value": false },
      "employee_population": ["tous"],
      "work_schedule": ["tous_regimes"],
      "application_period": { "label": "periode fictive ouverte", "start_date": "2026-01-01", "end_date": null, "notes": ["Periode synthetique pour tests uniquement."] },
      "source_layer": "synthetic_fixture",
      "source_document": "Fixture synthetique LOT 4D - duree hebdomadaire",
      "source_reference": "fixture:param:duree-hebdo",
      "effective_date": "2026-01-01",
      "end_date": null,
      "linked_rule_ids": ["PAY_HSUP_TRANCHES_001"],
      "linked_variables": ["seuil_declenchement", "semaine_ou_cycle"],
      "linked_nibelis_rubric_ids": ["NIB_RUB_HSUP_BASE"],
      "linked_kelio_counter_ids": ["KELIO_HS_SYN"],
      "calculation_allowed": false,
      "legal_priority": "to_verify",
      "validation_status": "synthetic_example",
      "human_validation": { "status": "pending", "validator": "expert_paie_humain", "validated_at": null, "notes": ["Valeur fictive non validee."] },
      "confidence": "low",
      "confidentiality": "internal",
      "verified_by": "expert_paie_humain",
      "last_checked_at": null,
      "validation_documents": ["accord temps de travail a verifier", "releve Kelio anonymise futur"],
      "misuse_risks": ["Declencher a tort des heures supplementaires."],
      "mutually_exclusive_group": null,
      "synthetic_only": true,
      "notes": ["Ne pas comparer a une duree legale ou conventionnelle."]
    },
    {
      "parameter_id": "PARAM_HSUP_SEUIL_SYN",
      "parameter_code": "HSUP_SEUIL_SYN",
      "label": "Seuil de declenchement heures supplementaires synthetique",
      "business_description": "Parametre fictif signalant qu'un seuil de declenchement doit etre source, date et valide.",
      "data_role": "source_data",
      "parameter_type": "threshold",
      "value_state": "awaiting_human_validation",
      "value_kind": "entered_data",
      "value": { "raw": "88,80 heures - seuil fictif non applicable", "numeric_value": 88.8, "unit": "hours", "currency": null, "percentage": null, "is_fallback_value": false },
      "employee_population": ["tous"],
      "work_schedule": ["tous_regimes"],
      "application_period": { "label": "periode fictive ouverte", "start_date": "2026-01-01", "end_date": null, "notes": ["Doit etre remplace par une source reelle avant usage."] },
      "source_layer": "synthetic_fixture",
      "source_document": "Fixture synthetique LOT 4D - seuil HS",
      "source_reference": "fixture:param:hsup-seuil",
      "effective_date": "2026-01-01",
      "end_date": null,
      "linked_rule_ids": ["PAY_HSUP_TRANCHES_001"],
      "linked_variables": ["seuil_declenchement", "heures_validees", "semaine_ou_cycle"],
      "linked_nibelis_rubric_ids": ["NIB_RUB_HSUP_BASE", "NIB_RUB_HSUP_MAJ"],
      "linked_kelio_counter_ids": ["KELIO_HS_SYN"],
      "calculation_allowed": false,
      "legal_priority": "to_verify",
      "validation_status": "synthetic_example",
      "human_validation": { "status": "pending", "validator": "expert_paie_humain", "validated_at": null, "notes": ["Validation humaine obligatoire avant toute interpretation."] },
      "confidence": "low",
      "confidentiality": "internal",
      "verified_by": "expert_paie_humain",
      "last_checked_at": null,
      "validation_documents": ["accord applicable", "export Kelio anonymise", "bulletin anonymise"],
      "misuse_risks": ["Payer ou reclamer des heures sur une base fictive."],
      "mutually_exclusive_group": "hsup_seuil_syn",
      "synthetic_only": true,
      "notes": ["Exemple de parametre en attente de validation humaine."]
    },
    {
      "parameter_id": "PARAM_HSUP_MAJ_SYN",
      "parameter_code": "HSUP_MAJ_SYN",
      "label": "Majoration heures supplementaires synthetique",
      "business_description": "Parametre fictif representant un niveau de majoration d'heures supplementaires.",
      "data_role": "source_data",
      "parameter_type": "rate",
      "value_state": "synthetic_test_value",
      "value_kind": "entered_data",
      "value": { "raw": "17,30% - taux fictif non applicable", "numeric_value": 17.3, "unit": "rate_percent", "currency": null, "percentage": 17.3, "is_fallback_value": false },
      "employee_population": ["tous"],
      "work_schedule": ["tous_regimes"],
      "application_period": { "label": "periode fictive ouverte", "start_date": "2026-01-01", "end_date": null, "notes": ["Taux pedagogique sans valeur juridique."] },
      "source_layer": "synthetic_fixture",
      "source_document": "Fixture synthetique LOT 4D - majoration HS",
      "source_reference": "fixture:param:hsup-majoration",
      "effective_date": "2026-01-01",
      "end_date": null,
      "linked_rule_ids": ["PAY_HSUP_TRANCHES_001"],
      "linked_variables": ["valeur_applicable", "heures_validees", "base_horaire"],
      "linked_nibelis_rubric_ids": ["NIB_RUB_HSUP_MAJ"],
      "linked_kelio_counter_ids": ["KELIO_HS_SYN"],
      "calculation_allowed": false,
      "legal_priority": "to_verify",
      "validation_status": "synthetic_example",
      "human_validation": { "status": "pending", "validator": "expert_paie_humain", "validated_at": null, "notes": ["Non valide pour calcul."] },
      "confidence": "low",
      "confidentiality": "internal",
      "verified_by": "expert_paie_humain",
      "last_checked_at": null,
      "validation_documents": ["accord applicable", "rubriques bulletin anonymisees"],
      "misuse_risks": ["Confondre un taux fictif avec un taux applicable."],
      "mutually_exclusive_group": "hsup_majoration_syn",
      "synthetic_only": true,
      "notes": ["Ne pas rapprocher automatiquement d'un bareme reel."]
    },
    {
      "parameter_id": "PARAM_NUIT_MAJ_SYN",
      "parameter_code": "NUIT_MAJ_SYN",
      "label": "Majoration nuit synthetique",
      "business_description": "Parametre fictif pour qualifier le besoin d'une source sur la majoration ou prime de nuit.",
      "data_role": "source_data",
      "parameter_type": "rate",
      "value_state": "synthetic_test_value",
      "value_kind": "entered_data",
      "value": { "raw": "18,70% - taux fictif non applicable", "numeric_value": 18.7, "unit": "rate_percent", "currency": null, "percentage": 18.7, "is_fallback_value": false },
      "employee_population": ["personnel_poste"],
      "work_schedule": ["5x8", "nuit"],
      "application_period": { "label": "periode fictive ouverte", "start_date": "2026-01-01", "end_date": null, "notes": ["Aucune valeur INEOS encodee."] },
      "source_layer": "synthetic_fixture",
      "source_document": "Fixture synthetique LOT 4D - nuit",
      "source_reference": "fixture:param:nuit",
      "effective_date": "2026-01-01",
      "end_date": null,
      "linked_rule_ids": [],
      "linked_variables": ["jour", "heures_travaillees"],
      "linked_nibelis_rubric_ids": ["NIB_RUB_NUIT"],
      "linked_kelio_counter_ids": ["KELIO_NUIT_SYN"],
      "calculation_allowed": false,
      "legal_priority": "to_verify",
      "validation_status": "synthetic_example",
      "human_validation": { "status": "pending", "validator": "expert_paie_humain", "validated_at": null, "notes": ["Source reelle a obtenir."] },
      "confidence": "low",
      "confidentiality": "internal",
      "verified_by": "expert_paie_humain",
      "last_checked_at": null,
      "validation_documents": ["accord primes a verifier", "compteur nuit anonymise", "bulletin anonymise"],
      "misuse_risks": ["Interpreter un indicateur de nuit comme taux applicable."],
      "mutually_exclusive_group": "nuit_majoration_syn",
      "synthetic_only": true,
      "notes": ["Parametre present pour controle de structure uniquement."]
    },
    {
      "parameter_id": "PARAM_DIMANCHE_MAJ_SYN",
      "parameter_code": "DIMANCHE_MAJ_SYN",
      "label": "Majoration dimanche synthetique",
      "business_description": "Parametre fictif pour suivre le besoin d'une source sur les dimanches travailles.",
      "data_role": "source_data",
      "parameter_type": "rate",
      "value_state": "synthetic_test_value",
      "value_kind": "entered_data",
      "value": { "raw": "21,90% - taux fictif non applicable", "numeric_value": 21.9, "unit": "rate_percent", "currency": null, "percentage": 21.9, "is_fallback_value": false },
      "employee_population": ["personnel_poste"],
      "work_schedule": ["5x8", "dimanche"],
      "application_period": { "label": "periode fictive ouverte", "start_date": "2026-01-01", "end_date": null, "notes": ["Faux taux pedagogique."] },
      "source_layer": "synthetic_fixture",
      "source_document": "Fixture synthetique LOT 4D - dimanche",
      "source_reference": "fixture:param:dimanche",
      "effective_date": "2026-01-01",
      "end_date": null,
      "linked_rule_ids": [],
      "linked_variables": ["jour", "heures_travaillees"],
      "linked_nibelis_rubric_ids": ["NIB_RUB_DIMANCHE"],
      "linked_kelio_counter_ids": ["KELIO_DIMANCHE_SYN"],
      "calculation_allowed": false,
      "legal_priority": "to_verify",
      "validation_status": "synthetic_example",
      "human_validation": { "status": "pending", "validator": "expert_paie_humain", "validated_at": null, "notes": ["Aucune validation."] },
      "confidence": "low",
      "confidentiality": "internal",
      "verified_by": "expert_paie_humain",
      "last_checked_at": null,
      "validation_documents": ["accord applicable", "planning anonymise", "bulletin anonymise"],
      "misuse_risks": ["Confondre presence le dimanche et droit chiffre."],
      "mutually_exclusive_group": "dimanche_majoration_syn",
      "synthetic_only": true,
      "notes": ["Ne cree pas de droit."]
    },
    {
      "parameter_id": "PARAM_FERIE_MAJ_SYN",
      "parameter_code": "FERIE_MAJ_SYN",
      "label": "Majoration jour ferie synthetique",
      "business_description": "Parametre fictif pour tester le rattachement des jours feries aux sources et rubriques.",
      "data_role": "source_data",
      "parameter_type": "rate",
      "value_state": "synthetic_test_value",
      "value_kind": "entered_data",
      "value": { "raw": "32,10% - taux fictif non applicable", "numeric_value": 32.1, "unit": "rate_percent", "currency": null, "percentage": 32.1, "is_fallback_value": false },
      "employee_population": ["tous"],
      "work_schedule": ["jour", "5x8"],
      "application_period": { "label": "periode fictive ouverte", "start_date": "2026-01-01", "end_date": null, "notes": ["Exemple pedagogique."] },
      "source_layer": "synthetic_fixture",
      "source_document": "Fixture synthetique LOT 4D - ferie",
      "source_reference": "fixture:param:ferie",
      "effective_date": "2026-01-01",
      "end_date": null,
      "linked_rule_ids": ["PAY_HOLIDAY_DAY_WORKED_001", "PAY_HOLIDAY_POSTED_NORMAL_001", "PAY_HOLIDAY_POSTED_REST_001"],
      "linked_variables": ["date_jour_ferie", "heures_travaillees", "base_de_calcul", "recuperation_accordee"],
      "linked_nibelis_rubric_ids": ["NIB_RUB_JOUR_FERIE"],
      "linked_kelio_counter_ids": ["KELIO_FERIE_SYN"],
      "calculation_allowed": false,
      "legal_priority": "to_verify",
      "validation_status": "synthetic_example",
      "human_validation": { "status": "pending", "validator": "expert_paie_humain", "validated_at": null, "notes": ["Source reelle requise."] },
      "confidence": "low",
      "confidentiality": "internal",
      "verified_by": "expert_paie_humain",
      "last_checked_at": null,
      "validation_documents": ["calendrier ferie", "planning anonymise", "bulletin anonymise"],
      "misuse_risks": ["Appliquer une majoration fictive a un jour ferie reel."],
      "mutually_exclusive_group": "ferie_majoration_syn",
      "synthetic_only": true,
      "notes": ["Le taux n'est ni legal, ni conventionnel, ni INEOS."]
    },
    {
      "parameter_id": "PARAM_ASTREINTE_VAL_SYN",
      "parameter_code": "ASTREINTE_VAL_SYN",
      "label": "Valorisation astreinte synthetique",
      "business_description": "Parametre fictif representant une valeur ou modalite de valorisation d'astreinte.",
      "data_role": "source_data",
      "parameter_type": "amount",
      "value_state": "awaiting_human_validation",
      "value_kind": "entered_data",
      "value": { "raw": "42,42 EUR - montant fictif en attente de source", "numeric_value": 42.42, "unit": "amount_eur", "currency": "EUR", "percentage": null, "is_fallback_value": false },
      "employee_population": ["salaries_astreinte"],
      "work_schedule": ["astreinte"],
      "application_period": { "label": "periode fictive ouverte", "start_date": "2026-01-01", "end_date": null, "notes": ["Montant fictif non source."] },
      "source_layer": "synthetic_fixture",
      "source_document": "Fixture synthetique LOT 4D - astreinte",
      "source_reference": "fixture:param:astreinte",
      "effective_date": "2026-01-01",
      "end_date": null,
      "linked_rule_ids": ["PAY_RAPPEL_ASTREINTE_001"],
      "linked_variables": ["planning_astreinte", "heure_appel"],
      "linked_nibelis_rubric_ids": ["NIB_RUB_ASTREINTE"],
      "linked_kelio_counter_ids": ["KELIO_ASTREINTE_SYN"],
      "calculation_allowed": false,
      "legal_priority": "to_verify",
      "validation_status": "synthetic_example",
      "human_validation": { "status": "pending", "validator": "expert_paie_humain", "validated_at": null, "notes": ["Aucune source reelle."] },
      "confidence": "low",
      "confidentiality": "internal",
      "verified_by": "expert_paie_humain",
      "last_checked_at": null,
      "validation_documents": ["accord astreinte a verifier", "planning anonymise", "bulletin anonymise"],
      "misuse_risks": ["Transformer une astreinte planifiee en montant du sans source."],
      "mutually_exclusive_group": "astreinte_valorisation_syn",
      "synthetic_only": true,
      "notes": ["Montant volontairement fictif."]
    },
    {
      "parameter_id": "PARAM_INTERVENTION_VAL_SYN",
      "parameter_code": "INTERVENTION_VAL_SYN",
      "label": "Valorisation intervention synthetique",
      "business_description": "Parametre fictif lie a une intervention pendant ou hors astreinte.",
      "data_role": "source_data",
      "parameter_type": "amount",
      "value_state": "synthetic_test_value",
      "value_kind": "entered_data",
      "value": { "raw": "55,55 EUR - montant fictif non applicable", "numeric_value": 55.55, "unit": "amount_eur", "currency": "EUR", "percentage": null, "is_fallback_value": false },
      "employee_population": ["salaries_astreinte"],
      "work_schedule": ["astreinte", "rappel"],
      "application_period": { "label": "periode fictive ouverte", "start_date": "2026-01-01", "end_date": null, "notes": ["Valeur de test uniquement."] },
      "source_layer": "synthetic_fixture",
      "source_document": "Fixture synthetique LOT 4D - intervention",
      "source_reference": "fixture:param:intervention",
      "effective_date": "2026-01-01",
      "end_date": null,
      "linked_rule_ids": ["PAY_RAPPEL_ASTREINTE_001", "PAY_RAPPEL_HORS_ASTREINTE_001"],
      "linked_variables": ["heure_debut_intervention", "heure_fin_intervention", "temps_deplacement"],
      "linked_nibelis_rubric_ids": ["NIB_RUB_INTERVENTION_ASTREINTE"],
      "linked_kelio_counter_ids": ["KELIO_INTERVENTION_SYN"],
      "calculation_allowed": false,
      "legal_priority": "to_verify",
      "validation_status": "synthetic_example",
      "human_validation": { "status": "pending", "validator": "expert_paie_humain", "validated_at": null, "notes": ["Non validee."] },
      "confidence": "low",
      "confidentiality": "internal",
      "verified_by": "expert_paie_humain",
      "last_checked_at": null,
      "validation_documents": ["accord applicable", "trace intervention anonymisee", "bulletin anonymise"],
      "misuse_risks": ["Compter une intervention fictive comme indemnite reelle."],
      "mutually_exclusive_group": "intervention_valorisation_syn",
      "synthetic_only": true,
      "notes": ["Aucune valeur reelle n'est encodee."]
    },
    {
      "parameter_id": "PARAM_REPOS_QUOTIDIEN_MIN_SYN",
      "parameter_code": "REPOS_QUOT_MIN_SYN",
      "label": "Repos quotidien minimal synthetique",
      "business_description": "Parametre fictif permettant de tracer le besoin d'une duree minimale de repos quotidien.",
      "data_role": "source_data",
      "parameter_type": "duration",
      "value_state": "synthetic_test_value",
      "value_kind": "entered_data",
      "value": { "raw": "99,90 heures - duree fictive manifestement non applicable", "numeric_value": 99.9, "unit": "hours", "currency": null, "percentage": null, "is_fallback_value": false },
      "employee_population": ["tous"],
      "work_schedule": ["tous_regimes"],
      "application_period": { "label": "periode fictive ouverte", "start_date": "2026-01-01", "end_date": null, "notes": ["Duree volontairement non realiste pour eviter toute confusion."] },
      "source_layer": "synthetic_fixture",
      "source_document": "Fixture synthetique LOT 4D - repos quotidien",
      "source_reference": "fixture:param:repos-quotidien",
      "effective_date": "2026-01-01",
      "end_date": null,
      "linked_rule_ids": ["WT_REPOS_QUOTIDIEN_001"],
      "linked_variables": ["heure_fin_poste", "heure_reprise_poste", "derogation_applicable"],
      "linked_nibelis_rubric_ids": [],
      "linked_kelio_counter_ids": ["KELIO_REPOS_QUOTIDIEN_SYN"],
      "calculation_allowed": false,
      "legal_priority": "to_verify",
      "validation_status": "synthetic_example",
      "human_validation": { "status": "pending", "validator": "expert_paie_humain", "validated_at": null, "notes": ["Source juridique a verifier."] },
      "confidence": "low",
      "confidentiality": "internal",
      "verified_by": "expert_paie_humain",
      "last_checked_at": null,
      "validation_documents": ["texte applicable", "planning anonymise", "accord temps de travail"],
      "misuse_risks": ["Presenter une duree fictive comme minimum applicable."],
      "mutually_exclusive_group": "repos_quotidien_min_syn",
      "synthetic_only": true,
      "notes": ["La valeur est volontairement absurde et non applicable."]
    },
    {
      "parameter_id": "PARAM_REPOS_HEBDO_MIN_SYN",
      "parameter_code": "REPOS_HEBDO_MIN_SYN",
      "label": "Repos hebdomadaire minimal synthetique",
      "business_description": "Parametre fictif pour documenter le besoin de verifier le repos hebdomadaire.",
      "data_role": "source_data",
      "parameter_type": "duration",
      "value_state": "identified_value_unknown",
      "value_kind": "source_data",
      "value": { "raw": "valeur reelle inconnue - aucun defaut", "numeric_value": null, "unit": "hours", "currency": null, "percentage": null, "is_fallback_value": false },
      "employee_population": ["tous"],
      "work_schedule": ["tous_regimes"],
      "application_period": { "label": "periode a verifier", "start_date": null, "end_date": null, "notes": ["Aucune periode reelle connue."] },
      "source_layer": "to_verify",
      "source_document": "Document reel a identifier hors GitHub",
      "source_reference": null,
      "effective_date": null,
      "end_date": null,
      "linked_rule_ids": [],
      "linked_variables": ["jour", "heures_travaillees"],
      "linked_nibelis_rubric_ids": [],
      "linked_kelio_counter_ids": ["KELIO_REPOS_HEBDO_SYN"],
      "calculation_allowed": false,
      "legal_priority": "to_verify",
      "validation_status": "to_verify",
      "human_validation": { "status": "pending", "validator": "expert_paie_humain", "validated_at": null, "notes": ["Valeur a rechercher."] },
      "confidence": "low",
      "confidentiality": "internal",
      "verified_by": "expert_paie_humain",
      "last_checked_at": null,
      "validation_documents": ["texte applicable", "planning anonymise"],
      "misuse_risks": ["Utiliser une valeur par defaut silencieuse."],
      "mutually_exclusive_group": "repos_hebdo_min_syn",
      "synthetic_only": true,
      "notes": ["Cas explicite de valeur inconnue sans valeur de secours."]
    },
    {
      "parameter_id": "PARAM_REPOS_COMP_PLAFOND_SYN",
      "parameter_code": "RC_PLAFOND_SYN",
      "label": "Plafond repos compensateur synthetique",
      "business_description": "Parametre fictif representant un seuil ou plafond de repos compensateur.",
      "data_role": "source_data",
      "parameter_type": "threshold",
      "value_state": "synthetic_test_value",
      "value_kind": "entered_data",
      "value": { "raw": "66,60 heures - plafond fictif non applicable", "numeric_value": 66.6, "unit": "hours", "currency": null, "percentage": null, "is_fallback_value": false },
      "employee_population": ["tous"],
      "work_schedule": ["tous_regimes"],
      "application_period": { "label": "periode fictive ouverte", "start_date": "2026-01-01", "end_date": null, "notes": ["Plafond fictif."] },
      "source_layer": "synthetic_fixture",
      "source_document": "Fixture synthetique LOT 4D - repos compensateur",
      "source_reference": "fixture:param:repos-comp",
      "effective_date": "2026-01-01",
      "end_date": null,
      "linked_rule_ids": ["PAY_HSUP_TRANCHES_001"],
      "linked_variables": ["repos_compensateur", "heures_validees"],
      "linked_nibelis_rubric_ids": ["NIB_RUB_REPOS_COMPENSATEUR"],
      "linked_kelio_counter_ids": ["KELIO_REPOS_COMP_SYN"],
      "calculation_allowed": false,
      "legal_priority": "to_verify",
      "validation_status": "synthetic_example",
      "human_validation": { "status": "pending", "validator": "expert_paie_humain", "validated_at": null, "notes": ["Non valide."] },
      "confidence": "low",
      "confidentiality": "internal",
      "verified_by": "expert_paie_humain",
      "last_checked_at": null,
      "validation_documents": ["accord applicable", "compteur Kelio anonymise"],
      "misuse_risks": ["Plafonner un droit sur une valeur fictive."],
      "mutually_exclusive_group": "repos_comp_plafond_syn",
      "synthetic_only": true,
      "notes": ["Fixture de controle uniquement."]
    },
    {
      "parameter_id": "PARAM_CP_ACQUISITION_SYN",
      "parameter_code": "CP_ACQ_SYN",
      "label": "Acquisition conges payes synthetique",
      "business_description": "Parametre fictif de composant de formule pour les conges payes.",
      "data_role": "source_data",
      "parameter_type": "formula_component",
      "value_state": "synthetic_test_value",
      "value_kind": "entered_data",
      "value": { "raw": "8,80 jours - valeur fictive non applicable", "numeric_value": 8.8, "unit": "days", "currency": null, "percentage": null, "is_fallback_value": false },
      "employee_population": ["tous"],
      "work_schedule": ["tous_regimes"],
      "application_period": { "label": "periode fictive ouverte", "start_date": "2026-01-01", "end_date": null, "notes": ["Aucune regle de CP reelle encodee."] },
      "source_layer": "synthetic_fixture",
      "source_document": "Fixture synthetique LOT 4D - CP",
      "source_reference": "fixture:param:cp-acquisition",
      "effective_date": "2026-01-01",
      "end_date": null,
      "linked_rule_ids": ["LEAVE_CP_ACQUISITION_001"],
      "linked_variables": ["mois_travailles", "periode_acquisition", "mode_decompte_ouvrable_ou_ouvre"],
      "linked_nibelis_rubric_ids": ["NIB_RUB_CP_COMPTEUR"],
      "linked_kelio_counter_ids": ["KELIO_CP_SYN"],
      "calculation_allowed": false,
      "legal_priority": "to_verify",
      "validation_status": "synthetic_example",
      "human_validation": { "status": "pending", "validator": "expert_paie_humain", "validated_at": null, "notes": ["Non valide."] },
      "confidence": "low",
      "confidentiality": "internal",
      "verified_by": "expert_paie_humain",
      "last_checked_at": null,
      "validation_documents": ["convention ou accord applicable", "compteur CP anonymise"],
      "misuse_risks": ["Acquerir des CP fictifs dans une simulation presentee comme reelle."],
      "mutually_exclusive_group": "cp_acquisition_syn",
      "synthetic_only": true,
      "notes": ["Valeur volontairement non exploitable."]
    },
    {
      "parameter_id": "PARAM_CP_INDEMNITE_METHODE_SYN",
      "parameter_code": "CP_INDEMNITE_METHODE_SYN",
      "label": "Methode indemnite conges payes synthetique",
      "business_description": "Parametre fictif indiquant qu'une methode de comparaison doit etre documentee.",
      "data_role": "derived_data",
      "parameter_type": "method",
      "value_state": "structurally_checked_not_applicable",
      "value_kind": "derived_data",
      "value": { "raw": "methode fictive de comparaison - aucune formule applicable", "numeric_value": null, "unit": "text", "currency": null, "percentage": null, "is_fallback_value": false },
      "employee_population": ["tous"],
      "work_schedule": ["tous_regimes"],
      "application_period": { "label": "periode fictive ouverte", "start_date": "2026-01-01", "end_date": null, "notes": ["Structure verifiee, contenu non applicable."] },
      "source_layer": "synthetic_fixture",
      "source_document": "Fixture synthetique LOT 4D - indemnite CP",
      "source_reference": "fixture:param:cp-indemnite",
      "effective_date": "2026-01-01",
      "end_date": null,
      "linked_rule_ids": ["LEAVE_CP_INDEMNITY_COMPARE_001"],
      "linked_variables": ["montant_maintien", "assiette_dixieme", "jours_conges_pris"],
      "linked_nibelis_rubric_ids": ["NIB_RUB_INDEMNITE_CP"],
      "linked_kelio_counter_ids": ["KELIO_CP_SYN"],
      "calculation_allowed": false,
      "legal_priority": "to_verify",
      "validation_status": "synthetic_example",
      "human_validation": { "status": "pending", "validator": "expert_paie_humain", "validated_at": null, "notes": ["Methode non validee."] },
      "confidence": "low",
      "confidentiality": "internal",
      "verified_by": "expert_paie_humain",
      "last_checked_at": null,
      "validation_documents": ["bulletin anonymise", "source juridique applicable"],
      "misuse_risks": ["Utiliser une methode de calcul non sourcee."],
      "mutually_exclusive_group": "cp_indemnite_methode_syn",
      "synthetic_only": true,
      "notes": ["Parametre de methode, pas de valeur chiffrable."]
    },
    {
      "parameter_id": "PARAM_MALADIE_MAINTIEN_SYN",
      "parameter_code": "MALADIE_MAINTIEN_SYN",
      "label": "Maintien maladie synthetique",
      "business_description": "Parametre fictif de taux ou niveau de maintien de salaire maladie.",
      "data_role": "source_data",
      "parameter_type": "rate",
      "value_state": "awaiting_human_validation",
      "value_kind": "entered_data",
      "value": { "raw": "45,60% - taux fictif en attente de source", "numeric_value": 45.6, "unit": "rate_percent", "currency": null, "percentage": 45.6, "is_fallback_value": false },
      "employee_population": ["tous"],
      "work_schedule": ["tous_regimes"],
      "application_period": { "label": "periode fictive ouverte", "start_date": "2026-01-01", "end_date": null, "notes": ["Source maladie a identifier."] },
      "source_layer": "synthetic_fixture",
      "source_document": "Fixture synthetique LOT 4D - maladie",
      "source_reference": "fixture:param:maladie-maintien",
      "effective_date": "2026-01-01",
      "end_date": null,
      "linked_rule_ids": ["PAY_MALADIE_MAINTIEN_001"],
      "linked_variables": ["anciennete", "duree_arret", "ijss", "salaire_reference"],
      "linked_nibelis_rubric_ids": ["NIB_RUB_MAINTIEN_MALADIE", "NIB_RUB_IJSS"],
      "linked_kelio_counter_ids": ["KELIO_ABSENCE_SYN"],
      "calculation_allowed": false,
      "legal_priority": "to_verify",
      "validation_status": "synthetic_example",
      "human_validation": { "status": "pending", "validator": "expert_paie_humain", "validated_at": null, "notes": ["Validation necessaire."] },
      "confidence": "low",
      "confidentiality": "internal",
      "verified_by": "expert_paie_humain",
      "last_checked_at": null,
      "validation_documents": ["source maintien maladie", "bulletin anonymise", "attestation non nominative si disponible"],
      "misuse_risks": ["Melanger maladie et donnees de sante individuelles."],
      "mutually_exclusive_group": "maladie_maintien_syn",
      "synthetic_only": true,
      "notes": ["Aucune donnee de sante ou arret reel."]
    },
    {
      "parameter_id": "PARAM_SUBROGATION_MODE_SYN",
      "parameter_code": "SUBROGATION_MODE_SYN",
      "label": "Modalite subrogation synthetique",
      "business_description": "Parametre informatif fictif indiquant qu'une modalite de subrogation doit etre verifiee.",
      "data_role": "controlled_data",
      "parameter_type": "method",
      "value_state": "identified_value_unknown",
      "value_kind": "controlled_data",
      "value": { "raw": "modalite reelle inconnue - aucun defaut", "numeric_value": null, "unit": "text", "currency": null, "percentage": null, "is_fallback_value": false },
      "employee_population": ["tous"],
      "work_schedule": ["tous_regimes"],
      "application_period": { "label": "periode a verifier", "start_date": null, "end_date": null, "notes": ["Aucune modalite reelle dans Git."] },
      "source_layer": "to_verify",
      "source_document": "Document reel a identifier hors GitHub",
      "source_reference": null,
      "effective_date": null,
      "end_date": null,
      "linked_rule_ids": ["PAY_MALADIE_MAINTIEN_001"],
      "linked_variables": ["ijss", "complement_prevoyance"],
      "linked_nibelis_rubric_ids": ["NIB_RUB_SUBROGATION", "NIB_RUB_IJSS"],
      "linked_kelio_counter_ids": ["KELIO_ABSENCE_SYN"],
      "calculation_allowed": false,
      "legal_priority": "to_verify",
      "validation_status": "to_verify",
      "human_validation": { "status": "pending", "validator": "expert_paie_humain", "validated_at": null, "notes": ["Parametre sans valeur exploitable."] },
      "confidence": "low",
      "confidentiality": "internal",
      "verified_by": "expert_paie_humain",
      "last_checked_at": null,
      "validation_documents": ["procedure subrogation a verifier", "bulletin anonymise"],
      "misuse_risks": ["Conclure sur une subrogation sans document source."],
      "mutually_exclusive_group": "subrogation_mode_syn",
      "synthetic_only": true,
      "notes": ["Cas de parametre identifie avec valeur inconnue."]
    },
    {
      "parameter_id": "PARAM_13E_MOIS_MODE_SYN",
      "parameter_code": "TREIZE_MOIS_MODE_SYN",
      "label": "Mode 13e mois synthetique",
      "business_description": "Parametre fictif representant une methode de controle du 13e mois.",
      "data_role": "derived_data",
      "parameter_type": "method",
      "value_state": "structurally_checked_not_applicable",
      "value_kind": "derived_data",
      "value": { "raw": "mode fictif de controle du 13e mois - non applicable", "numeric_value": null, "unit": "text", "currency": null, "percentage": null, "is_fallback_value": false },
      "employee_population": ["tous"],
      "work_schedule": ["tous_regimes"],
      "application_period": { "label": "periode fictive ouverte", "start_date": "2026-01-01", "end_date": null, "notes": ["Methode de structure uniquement."] },
      "source_layer": "synthetic_fixture",
      "source_document": "Fixture synthetique LOT 4D - 13e mois",
      "source_reference": "fixture:param:13e-mois",
      "effective_date": "2026-01-01",
      "end_date": null,
      "linked_rule_ids": ["PAY_13E_MOIS_001"],
      "linked_variables": ["salaire_reference", "presence", "mois_paiement", "montant_deja_verse"],
      "linked_nibelis_rubric_ids": ["NIB_RUB_13E_MOIS"],
      "linked_kelio_counter_ids": [],
      "calculation_allowed": false,
      "legal_priority": "to_verify",
      "validation_status": "synthetic_example",
      "human_validation": { "status": "pending", "validator": "expert_paie_humain", "validated_at": null, "notes": ["Aucune validation."] },
      "confidence": "low",
      "confidentiality": "internal",
      "verified_by": "expert_paie_humain",
      "last_checked_at": null,
      "validation_documents": ["accord ou usage a verifier", "bulletin anonymise"],
      "misuse_risks": ["Transformer une methode fictive en droit au versement."],
      "mutually_exclusive_group": "treize_mois_mode_syn",
      "synthetic_only": true,
      "notes": ["Aucun montant reel."]
    },
    {
      "parameter_id": "PARAM_ANCIENNETE_SEUIL_SYN",
      "parameter_code": "ANCIENNETE_SEUIL_SYN",
      "label": "Seuil anciennete synthetique",
      "business_description": "Parametre fictif pour relier anciennete, source et rubrique sans bareme reel.",
      "data_role": "source_data",
      "parameter_type": "threshold",
      "value_state": "synthetic_test_value",
      "value_kind": "entered_data",
      "value": { "raw": "3,70 unites - seuil fictif non applicable", "numeric_value": 3.7, "unit": "count", "currency": null, "percentage": null, "is_fallback_value": false },
      "employee_population": ["tous"],
      "work_schedule": ["tous_regimes"],
      "application_period": { "label": "periode fictive ouverte", "start_date": "2026-01-01", "end_date": null, "notes": ["Aucun bareme reel."] },
      "source_layer": "synthetic_fixture",
      "source_document": "Fixture synthetique LOT 4D - anciennete",
      "source_reference": "fixture:param:anciennete",
      "effective_date": "2026-01-01",
      "end_date": null,
      "linked_rule_ids": ["PAY_MALADIE_MAINTIEN_001"],
      "linked_variables": ["anciennete"],
      "linked_nibelis_rubric_ids": ["NIB_RUB_PRIME_ANCIENNETE"],
      "linked_kelio_counter_ids": [],
      "calculation_allowed": false,
      "legal_priority": "to_verify",
      "validation_status": "synthetic_example",
      "human_validation": { "status": "pending", "validator": "expert_paie_humain", "validated_at": null, "notes": ["Non valide."] },
      "confidence": "low",
      "confidentiality": "internal",
      "verified_by": "expert_paie_humain",
      "last_checked_at": null,
      "validation_documents": ["source anciennete", "historique anonymise si necessaire"],
      "misuse_risks": ["Utiliser un seuil fictif pour ouvrir ou fermer un droit."],
      "mutually_exclusive_group": "anciennete_seuil_syn",
      "synthetic_only": true,
      "notes": ["Ne contient aucun bareme."]
    },
    {
      "parameter_id": "PARAM_KM_VALEUR_SYN",
      "parameter_code": "KM_VALEUR_SYN",
      "label": "Indemnite kilometrique synthetique",
      "business_description": "Parametre fictif de valeur kilometrique a ne jamais utiliser comme bareme.",
      "data_role": "source_data",
      "parameter_type": "amount",
      "value_state": "synthetic_test_value",
      "value_kind": "entered_data",
      "value": { "raw": "0,42 EUR/km - valeur fictive non applicable", "numeric_value": 0.42, "unit": "amount_eur", "currency": "EUR", "percentage": null, "is_fallback_value": false },
      "employee_population": ["tous"],
      "work_schedule": ["tous_regimes"],
      "application_period": { "label": "periode fictive ouverte", "start_date": "2026-01-01", "end_date": null, "notes": ["Pas de bareme reel."] },
      "source_layer": "synthetic_fixture",
      "source_document": "Fixture synthetique LOT 4D - kilometres",
      "source_reference": "fixture:param:km",
      "effective_date": "2026-01-01",
      "end_date": null,
      "linked_rule_ids": ["PAY_INDEMNITE_KM_2023_001", "PAY_INDEMNITE_KM_DISTANCE_2026_001"],
      "linked_variables": ["distance_km", "nombre_trajets", "valeur_applicable"],
      "linked_nibelis_rubric_ids": ["NIB_RUB_INDEMNITE_KM"],
      "linked_kelio_counter_ids": [],
      "calculation_allowed": false,
      "legal_priority": "to_verify",
      "validation_status": "synthetic_example",
      "human_validation": { "status": "pending", "validator": "expert_paie_humain", "validated_at": null, "notes": ["Non validee."] },
      "confidence": "low",
      "confidentiality": "internal",
      "verified_by": "expert_paie_humain",
      "last_checked_at": null,
      "validation_documents": ["bareme reel a verifier", "distance anonymisee ou methode"],
      "misuse_risks": ["Appliquer une valeur fictive a un trajet reel."],
      "mutually_exclusive_group": "km_valeur_syn",
      "synthetic_only": true,
      "notes": ["Aucune adresse reelle, aucun trajet reel."]
    },
    {
      "parameter_id": "PARAM_PANIER_REPAS_SYN",
      "parameter_code": "PANIER_REPAS_SYN",
      "label": "Panier repas synthetique",
      "business_description": "Parametre fictif pour representer une indemnite ou panier repas.",
      "data_role": "source_data",
      "parameter_type": "amount",
      "value_state": "awaiting_human_validation",
      "value_kind": "entered_data",
      "value": { "raw": "6,66 EUR - montant fictif non applicable", "numeric_value": 6.66, "unit": "amount_eur", "currency": "EUR", "percentage": null, "is_fallback_value": false },
      "employee_population": ["tous"],
      "work_schedule": ["jour", "5x8"],
      "application_period": { "label": "periode fictive ouverte", "start_date": "2026-01-01", "end_date": null, "notes": ["Montant pedagogique."] },
      "source_layer": "synthetic_fixture",
      "source_document": "Fixture synthetique LOT 4D - panier repas",
      "source_reference": "fixture:param:panier",
      "effective_date": "2026-01-01",
      "end_date": null,
      "linked_rule_ids": [],
      "linked_variables": ["periode"],
      "linked_nibelis_rubric_ids": ["NIB_RUB_PANIER_REPAS"],
      "linked_kelio_counter_ids": [],
      "calculation_allowed": false,
      "legal_priority": "to_verify",
      "validation_status": "synthetic_example",
      "human_validation": { "status": "pending", "validator": "expert_paie_humain", "validated_at": null, "notes": ["Validation humaine necessaire."] },
      "confidence": "low",
      "confidentiality": "internal",
      "verified_by": "expert_paie_humain",
      "last_checked_at": null,
      "validation_documents": ["source panier a verifier", "bulletin anonymise"],
      "misuse_risks": ["Communiquer un montant panier fictif."],
      "mutually_exclusive_group": "panier_repas_syn",
      "synthetic_only": true,
      "notes": ["Montant fictif."]
    },
    {
      "parameter_id": "PARAM_PLAFOND_INTERNE_SYN",
      "parameter_code": "PLAFOND_INTERNE_SYN",
      "label": "Plafond interne fictif a sourcer",
      "business_description": "Parametre de plafond fictif dont la valeur reelle n'est pas connue.",
      "data_role": "source_data",
      "parameter_type": "ceiling",
      "value_state": "awaiting_source",
      "value_kind": "source_data",
      "value": { "raw": "valeur inconnue - aucun plafond par defaut", "numeric_value": null, "unit": "amount_eur", "currency": null, "percentage": null, "is_fallback_value": false },
      "employee_population": ["tous"],
      "work_schedule": ["tous_regimes"],
      "application_period": { "label": "periode a verifier", "start_date": null, "end_date": null, "notes": ["Source reelle absente."] },
      "source_layer": "to_verify",
      "source_document": "Document interne reel a identifier hors GitHub",
      "source_reference": null,
      "effective_date": null,
      "end_date": null,
      "linked_rule_ids": [],
      "linked_variables": ["valeur_applicable"],
      "linked_nibelis_rubric_ids": ["NIB_RUB_PRIME_EXCEPTIONNELLE"],
      "linked_kelio_counter_ids": [],
      "calculation_allowed": false,
      "legal_priority": "to_verify",
      "validation_status": "to_verify",
      "human_validation": { "status": "pending", "validator": "expert_paie_humain", "validated_at": null, "notes": ["Aucune valeur exploitable."] },
      "confidence": "low",
      "confidentiality": "internal",
      "verified_by": "expert_paie_humain",
      "last_checked_at": null,
      "validation_documents": ["document interne a demander", "validation humaine"],
      "misuse_risks": ["Remplacer une valeur inconnue par un plafond arbitraire."],
      "mutually_exclusive_group": "plafond_interne_syn",
      "synthetic_only": true,
      "notes": ["Cas de valeur inconnue avec documents a obtenir."]
    },
    {
      "parameter_id": "PARAM_REGULARISATION_DATE_SYN",
      "parameter_code": "REGULARISATION_DATE_SYN",
      "label": "Date de regularisation synthetique",
      "business_description": "Parametre fictif de date ou periode de regularisation.",
      "data_role": "source_data",
      "parameter_type": "date",
      "value_state": "synthetic_test_value",
      "value_kind": "entered_data",
      "value": { "raw": "2099-09-09 - date fictive non applicable", "numeric_value": null, "unit": "date", "currency": null, "percentage": null, "is_fallback_value": false },
      "employee_population": ["tous"],
      "work_schedule": ["5x8"],
      "application_period": { "label": "periode fictive cible", "start_date": "2026-01-01", "end_date": null, "notes": ["Date pedagogique future."] },
      "source_layer": "synthetic_fixture",
      "source_document": "Fixture synthetique LOT 4D - regularisation",
      "source_reference": "fixture:param:regularisation-date",
      "effective_date": "2026-01-01",
      "end_date": null,
      "linked_rule_ids": ["WT_5X8_JR_REGULARISATION_001", "WT_5X8_RJFJ_TO_JR_001"],
      "linked_variables": ["date_regularisation", "solde_JR"],
      "linked_nibelis_rubric_ids": ["NIB_RUB_REGULARISATION_PAIE"],
      "linked_kelio_counter_ids": ["KELIO_JR_SYN", "KELIO_RJFJ_SYN"],
      "calculation_allowed": false,
      "legal_priority": "to_verify",
      "validation_status": "synthetic_example",
      "human_validation": { "status": "pending", "validator": "expert_paie_humain", "validated_at": null, "notes": ["Date non validee."] },
      "confidence": "low",
      "confidentiality": "internal",
      "verified_by": "expert_paie_humain",
      "last_checked_at": null,
      "validation_documents": ["note regularisation a verifier", "compteurs anonymises"],
      "misuse_risks": ["Utiliser une date fictive pour reclamer une regularisation."],
      "mutually_exclusive_group": "regularisation_date_syn",
      "synthetic_only": true,
      "notes": ["Date volontairement future et fictive."]
    },
    {
      "parameter_id": "PARAM_INFO_SANS_VALEUR_SYN",
      "parameter_code": "INFO_SANS_VALEUR_SYN",
      "label": "Parametre informatif sans valeur exploitable",
      "business_description": "Parametre informatif permettant de documenter un besoin de controle sans valeur de calcul.",
      "data_role": "controlled_data",
      "parameter_type": "informational",
      "value_state": "identified_value_unknown",
      "value_kind": "controlled_data",
      "value": { "raw": "information a qualifier - aucune valeur exploitable", "numeric_value": null, "unit": "none", "currency": null, "percentage": null, "is_fallback_value": false },
      "employee_population": ["tous"],
      "work_schedule": ["tous_regimes"],
      "application_period": { "label": "periode non determinee", "start_date": null, "end_date": null, "notes": ["Pas de valeur et pas de periode."] },
      "source_layer": "to_verify",
      "source_document": "Source future a identifier hors GitHub",
      "source_reference": null,
      "effective_date": null,
      "end_date": null,
      "linked_rule_ids": [],
      "linked_variables": ["compteurs_kelio"],
      "linked_nibelis_rubric_ids": ["NIB_RUB_COMPTEURS_INFO"],
      "linked_kelio_counter_ids": ["KELIO_POINTAGE_SYN"],
      "calculation_allowed": false,
      "legal_priority": "to_verify",
      "validation_status": "to_verify",
      "human_validation": { "status": "pending", "validator": "expert_paie_humain", "validated_at": null, "notes": ["Information a qualifier."] },
      "confidence": "low",
      "confidentiality": "internal",
      "verified_by": "expert_paie_humain",
      "last_checked_at": null,
      "validation_documents": ["document explicatif a demander"],
      "misuse_risks": ["Interpreter une information comme une valeur de calcul."],
      "mutually_exclusive_group": null,
      "synthetic_only": true,
      "notes": ["Cas volontairement sans valeur exploitable."]
    }
  ]
}
